   { "type" : "FeatureCollection" , "crs" : { "type" : "name" , "properties" : { "name" : "EPSG:2169"}} , "features" : [ { "type" : "Feature" , "bbox" : [ 78985.02 , 76212.4 , 78985.02 , 76212.4] , "geometry" : { "type" : "Point" , "coordinates" : [ 78985.02 , 76212.4]} , "properties" : { "name" : "Ligne autobus: 20 / Bleuets<br>Direction(s): Marcel Reuland"}} , { "type" : "Feature" , "bbox" : [ 76989.28 , 75407.72 , 77197.77 , 75724.34] , "geometry" : { "type" : "LineString" , "coordinates" : [ [ 76989.28 , 75724.34] , [ 77021.63 , 75630.88] , [ 77043.54 , 75567.78] , [ 77046.64 , 75557.96] , [ 77046.72 , 75557.7] , [ 77051.7 , 75537.87] , [ 77060.87 , 75511.53] , [ 77073.4 , 75472.63] , [ 77074.44 , 75468.7] , [ 77081.7 , 75448.2] , [ 77088.29 , 75432.01] , [ 77094.26 , 75415.45] , [ 77097.58 , 75410.24] , [ 77101.77 , 75408.56] , [ 77105.55 , 75407.72] , [ 77108.06 , 75408.21] , [ 77122.5 , 75412.3] , [ 77184.9 , 75431.51] , [ 77186.62 , 75431.99] , [ 77195.28 , 75433.02] , [ 77197.77 , 75433.49]]} , "properties" : { "name" : "Ligne autobus: 20"}} , { "type" : "Feature" , "bbox" : [ 79704.59 , 76894.37 , 79704.59 , 76894.37] , "geometry" : { "type" : "Point" , "coordinates" : [ 79704.59 , 76894.37]} , "properties" : { "name" : "Ligne autobus: 20 / Muguets<br>Direction(s): Marcel Reuland"}} , { "type" : "Feature" , "bbox" : [ 79446.95 , 76548.26 , 79670.51 , 76860.78] , "geometry" : { "type" : "LineString" , "coordinates" : [ [ 79670.51 , 76860.78] , [ 79663.0 , 76851.0] , [ 79630.0 , 76806.0] , [ 79616.86 , 76786.73] , [ 79552.3 , 76662.37] , [ 79542.46 , 76645.76] , [ 79539.39 , 76640.84] , [ 79531.39 , 76631.01] , [ 79521.14 , 76619.12] , [ 79506.79 , 76604.76] , [ 79499.41 , 76598.0] , [ 79474.61 , 76574.02] , [ 79461.28 , 76562.33] , [ 79446.95 , 76548.26]]} , "properties" : { "name" : "Ligne autobus: 20"}} , { "type" : "Feature" , "bbox" : [ 78985.02 , 76212.4 , 79344 , 76442.58] , "geometry" : { "type" : "LineString" , "coordinates" : [ [ 78985.02 , 76212.4] , [ 78992.0 , 76216.0] , [ 79015.65 , 76230.06] , [ 79031.84 , 76241.87] , [ 79032.66 , 76242.76] , [ 79054.34 , 76256.78] , [ 79113.33 , 76294.35] , [ 79160.0 , 76324.0] , [ 79199.0 , 76349.0] , [ 79213.87 , 76358.58] , [ 79229.83 , 76368.27] , [ 79273.11 , 76395.07] , [ 79306.93 , 76417.41] , [ 79329.27 , 76432.17] , [ 79343.93 , 76442.52] , [ 79344.0 , 76442.58]]} , "properties" : { "name" : "Ligne autobus: 20"}} , { "type" : "Feature" , "bbox" : [ 77028.13 , 75412.99 , 77182.41 , 75652.49] , "geometry" : { "type" : "LineString" , "coordinates" : [ [ 77182.41 , 75436.86] , [ 77112.53 , 75413.55] , [ 77110.21 , 75413.0] , [ 77109.6 , 75412.99] , [ 77109.0 , 75413.1] , [ 77108.41 , 75413.4] , [ 77108.0 , 75413.7] , [ 77107.5 , 75414.11] , [ 77107.1 , 75414.87] , [ 77104.38 , 75422.21] , [ 77094.2 , 75450.5] , [ 77083.68 , 75479.23] , [ 77082.45 , 75482.89] , [ 77061.53 , 75541.51] , [ 77059.9 , 75547.66] , [ 77059.49 , 75551.35] , [ 77058.87 , 75561.19] , [ 77058.92 , 75561.24] , [ 77028.13 , 75652.49]]} , "properties" : { "name" : "Ligne autobus: 20"}} , { "type" : "Feature" , "bbox" : [ 77957.51 , 75147.91 , 78193 , 75276] , "geometry" : { "type" : "LineString" , "coordinates" : [ [ 77957.51 , 75147.91] , [ 78066.0 , 75196.19] , [ 78096.48 , 75209.47] , [ 78123.94 , 75221.61] , [ 78132.73 , 75225.63] , [ 78144.38 , 75232.25] , [ 78149.66 , 75235.73] , [ 78164.59 , 75246.13] , [ 78190.94 , 75273.73] , [ 78193.0 , 75276.0] , [ 78190.94 , 75273.73]]} , "properties" : { "name" : "Ligne autobus: 20"}} , { "type" : "Feature" , "bbox" : [ 78765.24 , 75197.51 , 79225.93 , 75347.61] , "geometry" : { "type" : "LineString" , "coordinates" : [ [ 78765.24 , 75197.51] , [ 78781.69 , 75204.2] , [ 78793.89 , 75209.11] , [ 78862.73 , 75236.29] , [ 78918.07 , 75253.1] , [ 78966.86 , 75267.45] , [ 79024.87 , 75283.64] , [ 79159.43 , 75323.56] , [ 79225.93 , 75347.61]]} , "properties" : { "name" : "Ligne autobus: 20"}} , { "type" : "Feature" , "bbox" : [ 78860.49 , 75243.32 , 79218.01 , 75352.72] , "geometry" : { "type" : "LineString" , "coordinates" : [ [ 79218.01 , 75352.72] , [ 79172.28 , 75336.21] , [ 79111.06 , 75316.54] , [ 79074.3 , 75305.77] , [ 79050.9 , 75299.46] , [ 79035.17 , 75294.88] , [ 79026.13 , 75292.65] , [ 78984.28 , 75280.19] , [ 78920.38 , 75261.74] , [ 78867.64 , 75245.84] , [ 78864.15 , 75244.63] , [ 78860.49 , 75243.32]]} , "properties" : { "name" : "Ligne autobus: 20"}} , { "type" : "Feature" , "bbox" : [ 79299.9 , 76422.08 , 79299.9 , 76422.08] , "geometry" : { "type" : "Point" , "coordinates" : [ 79299.9 , 76422.08]} , "properties" : { "name" : "Ligne autobus: 20 / Pâquerettes<br>Direction(s): Rue de Bitbourg / Fondation Pescatore"}} , { "type" : "Feature" , "bbox" : [ 79344 , 76442.58 , 79344 , 76442.58] , "geometry" : { "type" : "Point" , "coordinates" : [ 79344.0 , 76442.58]} , "properties" : { "name" : "Ligne autobus: 20 / Pâquerettes<br>Direction(s): Marcel Reuland"}} , { "type" : "Feature" , "bbox" : [ 79446.95 , 76548.26 , 79446.95 , 76548.26] , "geometry" : { "type" : "Point" , "coordinates" : [ 79446.95 , 76548.26]} , "properties" : { "name" : "Ligne autobus: 20 / Marguerites<br>Direction(s): Rue de Bitbourg / Fondation Pescatore"}} , { "type" : "Feature" , "bbox" : [ 79493.44 , 76581.92 , 79493.44 , 76581.92] , "geometry" : { "type" : "Point" , "coordinates" : [ 79493.44 , 76581.92]} , "properties" : { "name" : "Ligne autobus: 20 / Marguerites<br>Direction(s): Marcel Reuland"}} , { "type" : "Feature" , "bbox" : [ 79955.77 , 77777.95 , 80076.97 , 77899.05] , "geometry" : { "type" : "LineString" , "coordinates" : [ [ 79955.77 , 77777.95] , [ 80015.95 , 77837.72] , [ 80033.45 , 77856.35] , [ 80076.97 , 77899.05]]} , "properties" : { "name" : "Ligne autobus: 20"}} , { "type" : "Feature" , "bbox" : [ 79218.01 , 75352.72 , 79535.72 , 75479.13] , "geometry" : { "type" : "LineString" , "coordinates" : [ [ 79535.72 , 75479.13] , [ 79516.99 , 75472.89] , [ 79469.98 , 75457.79] , [ 79436.74 , 75444.84] , [ 79323.07 , 75396.83] , [ 79241.65 , 75361.85] , [ 79229.3 , 75357.12] , [ 79218.01 , 75352.72]]} , "properties" : { "name" : "Ligne autobus: 20"}} , { "type" : "Feature" , "bbox" : [ 79225.93 , 75347.61 , 79619.42 , 75507.31] , "geometry" : { "type" : "LineString" , "coordinates" : [ [ 79225.93 , 75347.61] , [ 79235.59 , 75351.2] , [ 79269.83 , 75365.84] , [ 79305.5 , 75380.39] , [ 79341.98 , 75396.39] , [ 79378.88 , 75413.4] , [ 79415.17 , 75428.56] , [ 79464.36 , 75448.86] , [ 79506.59 , 75462.8] , [ 79529.55 , 75470.59] , [ 79551.66 , 75477.89] , [ 79582.73 , 75490.79] , [ 79589.62 , 75493.8] , [ 79601.87 , 75499.33] , [ 79619.42 , 75507.31]]} , "properties" : { "name" : "Ligne autobus: 20"}} , { "type" : "Feature" , "bbox" : [ 80420.15 , 75585.39 , 80420.15 , 75585.39] , "geometry" : { "type" : "Point" , "coordinates" : [ 80420.15 , 75585.39]} , "properties" : { "name" : "Ligne autobus: 20 / Ronndréisch Quai 2<br>Direction(s): Marcel Reuland"}} , { "type" : "Feature" , "bbox" : [ 79619.42 , 75507.31 , 79763.34 , 75567.9] , "geometry" : { "type" : "LineString" , "coordinates" : [ [ 79619.42 , 75507.31] , [ 79622.68 , 75508.78] , [ 79635.02 , 75514.35] , [ 79744.49 , 75565.84] , [ 79748.93 , 75567.5] , [ 79750.86 , 75567.89] , [ 79752.18 , 75567.9] , [ 79754.18 , 75567.5] , [ 79756.55 , 75566.04] , [ 79759.44 , 75561.73] , [ 79761.06 , 75558.57] , [ 79762.31 , 75556.05] , [ 79763.11 , 75553.18] , [ 79763.34 , 75550.07] , [ 79762.36 , 75547.64] , [ 79760.74 , 75545.52] , [ 79756.52 , 75541.46] , [ 79712.32 , 75514.01] , [ 79711.59 , 75513.57]]} , "properties" : { "name" : "Ligne autobus: 20"}} , { "type" : "Feature" , "bbox" : [ 80067.9 , 75362.88 , 80353.72 , 75499.41] , "geometry" : { "type" : "LineString" , "coordinates" : [ [ 80353.72 , 75482.35] , [ 80278.64 , 75497.22] , [ 80269.25 , 75499.41] , [ 80262.05 , 75499.1] , [ 80251.4 , 75496.28] , [ 80182.67 , 75453.54] , [ 80095.85 , 75400.06] , [ 80080.94 , 75390.58] , [ 80077.6 , 75388.45] , [ 80072.6 , 75383.54] , [ 80069.77 , 75378.85] , [ 80067.9 , 75373.21] , [ 80069.15 , 75368.51] , [ 80071.97 , 75365.38] , [ 80077.6 , 75363.82] , [ 80082.93 , 75362.88] , [ 80090.45 , 75365.7] , [ 80091.61 , 75366.39] , [ 80133.26 , 75392.64]]} , "properties" : { "name" : "Ligne autobus: 20"}} , { "type" : "Feature" , "bbox" : [ 79299.9 , 76422.08 , 79446.95 , 76548.26] , "geometry" : { "type" : "LineString" , "coordinates" : [ [ 79446.95 , 76548.26] , [ 79336.24 , 76447.34] , [ 79328.25 , 76442.01] , [ 79318.82 , 76435.04] , [ 79299.9 , 76422.08]]} , "properties" : { "name" : "Ligne autobus: 20"}} , { "type" : "Feature" , "bbox" : [ 78126.51 , 75231.22 , 78254.16 , 75391.34] , "geometry" : { "type" : "LineString" , "coordinates" : [ [ 78224.89 , 75391.3] , [ 78224.89 , 75391.34] , [ 78229.54 , 75387.03] , [ 78235.47 , 75382.06] , [ 78244.78 , 75374.16] , [ 78251.23 , 75368.76] , [ 78253.49 , 75365.56] , [ 78254.16 , 75362.09] , [ 78252.83 , 75358.76] , [ 78247.33 , 75350.52] , [ 78246.0 , 75349.0] , [ 78224.0 , 75324.0] , [ 78219.62 , 75319.86] , [ 78204.25 , 75302.32] , [ 78182.86 , 75279.27] , [ 78160.08 , 75254.72] , [ 78145.88 , 75243.65] , [ 78135.22 , 75236.23] , [ 78126.51 , 75231.22]]} , "properties" : { "name" : "Ligne autobus: 20"}} , { "type" : "Feature" , "bbox" : [ 79344 , 76442.58 , 79493.44 , 76581.92] , "geometry" : { "type" : "LineString" , "coordinates" : [ [ 79344.0 , 76442.58] , [ 79359.61 , 76455.74] , [ 79434.63 , 76525.24] , [ 79464.98 , 76553.11] , [ 79493.44 , 76581.92]]} , "properties" : { "name" : "Ligne autobus: 20"}} , { "type" : "Feature" , "bbox" : [ 77905.54 , 75133.32 , 78126.51 , 75231.22] , "geometry" : { "type" : "LineString" , "coordinates" : [ [ 78126.51 , 75231.22] , [ 78123.88 , 75229.99] , [ 78078.45 , 75210.09] , [ 78037.74 , 75192.18] , [ 78006.53 , 75178.48] , [ 77997.67 , 75174.55] , [ 77990.1 , 75170.77] , [ 77982.26 , 75166.7] , [ 77957.65 , 75155.3] , [ 77953.13 , 75153.08] , [ 77935.03 , 75145.15] , [ 77913.79 , 75136.47] , [ 77905.54 , 75133.32]]} , "properties" : { "name" : "Ligne autobus: 20"}} , { "type" : "Feature" , "bbox" : [ 77868.56 , 75109.61 , 78149.38 , 75154.6] , "geometry" : { "type" : "LineString" , "coordinates" : [ [ 78149.38 , 75154.6] , [ 78095.88 , 75142.0] , [ 78067.18 , 75137.9] , [ 78018.81 , 75130.94] , [ 77992.37 , 75127.45] , [ 77978.56 , 75125.91] , [ 77965.52 , 75124.38] , [ 77941.84 , 75121.04] , [ 77869.38 , 75109.61] , [ 77868.56 , 75110.43] , [ 77868.77 , 75111.66] , [ 77870.47 , 75112.99] , [ 77869.79 , 75112.69] , [ 77872.66 , 75113.92] , [ 77883.11 , 75117.19] , [ 77898.49 , 75122.32] , [ 77904.22 , 75124.38] , [ 77957.51 , 75147.91]]} , "properties" : { "name" : "Ligne autobus: 20"}} , { "type" : "Feature" , "bbox" : [ 78978.8 , 76218.9 , 79299.9 , 76422.08] , "geometry" : { "type" : "LineString" , "coordinates" : [ [ 79299.9 , 76422.08] , [ 79299.35 , 76421.92] , [ 79259.69 , 76397.28] , [ 79178.82 , 76345.25] , [ 79176.0 , 76343.0] , [ 79162.0 , 76334.0] , [ 79161.19 , 76334.19] , [ 79078.58 , 76281.3] , [ 79022.0 , 76244.0] , [ 79014.3 , 76239.42] , [ 78996.0 , 76229.0] , [ 78979.23 , 76219.13] , [ 78978.81 , 76218.9] , [ 78978.8 , 76218.9]]} , "properties" : { "name" : "Ligne autobus: 20"}} , { "type" : "Feature" , "bbox" : [ 78149.38 , 75154.6 , 78517.56 , 75312] , "geometry" : { "type" : "LineString" , "coordinates" : [ [ 78517.56 , 75312.0] , [ 78517.4 , 75311.97] , [ 78508.61 , 75310.81] , [ 78478.23 , 75306.55] , [ 78464.17 , 75304.61] , [ 78451.0 , 75303.0] , [ 78421.0 , 75296.0] , [ 78410.0 , 75294.0] , [ 78402.0 , 75291.0] , [ 78396.0 , 75288.0] , [ 78370.0 , 75270.0] , [ 78356.0 , 75262.0] , [ 78310.0 , 75231.0] , [ 78282.0 , 75214.0] , [ 78245.0 , 75194.0] , [ 78229.0 , 75186.0] , [ 78220.0 , 75181.0] , [ 78187.0 , 75167.0] , [ 78149.38 , 75154.6]]} , "properties" : { "name" : "Ligne autobus: 20"}} , { "type" : "Feature" , "bbox" : [ 77604.8 , 75208.51 , 77971.03 , 75354.33] , "geometry" : { "type" : "LineString" , "coordinates" : [ [ 77604.8 , 75226.61] , [ 77629.04 , 75213.03] , [ 77636.82 , 75209.74] , [ 77644.21 , 75208.51] , [ 77651.99 , 75209.74] , [ 77665.94 , 75213.85] , [ 77688.07 , 75222.05] , [ 77735.63 , 75235.17] , [ 77765.96 , 75243.36] , [ 77799.99 , 75252.79] , [ 77829.92 , 75263.05] , [ 77852.47 , 75274.93] , [ 77884.04 , 75292.15] , [ 77909.87 , 75306.09] , [ 77931.6 , 75317.16] , [ 77971.03 , 75354.33]]} , "properties" : { "name" : "Ligne autobus: 20"}} , { "type" : "Feature" , "bbox" : [ 77905.54 , 75133.32 , 77905.54 , 75133.32] , "geometry" : { "type" : "Point" , "coordinates" : [ 77905.54 , 75133.32]} , "properties" : { "name" : "Ligne autobus: 20 / Rumm<br>Direction(s): Rue de Bitbourg / Fondation Pescatore"}} , { "type" : "Feature" , "bbox" : [ 77946.11 , 76308.23 , 78385.26 , 76682.01] , "geometry" : { "type" : "LineString" , "coordinates" : [ [ 77946.11 , 76308.23] , [ 77951.86 , 76317.77] , [ 77962.38 , 76334.71] , [ 77978.2 , 76356.42] , [ 77994.06 , 76375.34] , [ 78013.79 , 76397.68] , [ 78026.74 , 76412.01] , [ 78060.56 , 76443.99] , [ 78092.1 , 76472.17] , [ 78105.66 , 76484.22] , [ 78116.62 , 76495.34] , [ 78129.27 , 76506.45] , [ 78152.89 , 76523.37] , [ 78220.68 , 76571.06] , [ 78345.31 , 76656.83] , [ 78366.26 , 76670.03] , [ 78366.8 , 76670.3] , [ 78383.35 , 76680.77] , [ 78385.26 , 76682.01]]} , "properties" : { "name" : "Ligne autobus: 20"}} , { "type" : "Feature" , "bbox" : [ 78022.98 , 75123.98 , 78165.56 , 75152.5] , "geometry" : { "type" : "LineString" , "coordinates" : [ [ 78022.98 , 75123.98] , [ 78026.09 , 75124.4] , [ 78091.36 , 75133.97] , [ 78132.68 , 75142.91] , [ 78150.87 , 75147.85] , [ 78165.56 , 75152.5]]} , "properties" : { "name" : "Ligne autobus: 20"}} , { "type" : "Feature" , "bbox" : [ 78190.94 , 75273.73 , 78262.43 , 75403.47] , "geometry" : { "type" : "LineString" , "coordinates" : [ [ 78190.94 , 75273.73] , [ 78208.73 , 75292.97] , [ 78225.54 , 75311.42] , [ 78238.25 , 75326.59] , [ 78249.73 , 75339.29] , [ 78260.89 , 75353.55] , [ 78261.78 , 75354.96] , [ 78262.43 , 75356.52] , [ 78262.43 , 75360.62] , [ 78262.04 , 75362.61] , [ 78260.64 , 75367.33] , [ 78260.62 , 75367.36] , [ 78257.32 , 75372.6] , [ 78257.29 , 75372.63] , [ 78244.68 , 75383.13] , [ 78244.42 , 75383.33] , [ 78231.74 , 75393.83] , [ 78229.68 , 75395.7] , [ 78225.8 , 75399.48] , [ 78222.87 , 75403.47]]} , "properties" : { "name" : "Ligne autobus: 20"}} , { "type" : "Feature" , "bbox" : [ 77970.84 , 75354.24 , 78224.89 , 75458.24] , "geometry" : { "type" : "LineString" , "coordinates" : [ [ 77971.03 , 75354.33] , [ 77971.04 , 75354.34] , [ 77970.84 , 75354.24] , [ 77973.72 , 75356.85] , [ 77976.56 , 75359.52] , [ 77978.73 , 75361.54] , [ 77983.63 , 75366.14] , [ 77990.33 , 75372.74] , [ 78006.53 , 75390.44] , [ 78007.04 , 75390.94] , [ 78037.34 , 75428.14] , [ 78048.14 , 75439.74] , [ 78052.53 , 75444.24] , [ 78057.53 , 75448.44] , [ 78064.54 , 75452.34] , [ 78071.14 , 75455.44] , [ 78076.64 , 75456.94] , [ 78083.63 , 75458.04] , [ 78092.73 , 75458.24] , [ 78115.54 , 75456.94] , [ 78134.24 , 75454.64] , [ 78146.13 , 75452.54] , [ 78161.44 , 75449.34] , [ 78172.54 , 75445.94] , [ 78179.24 , 75443.64] , [ 78183.07 , 75441.61] , [ 78188.0 , 75438.0] , [ 78199.0 , 75429.0] , [ 78202.41 , 75425.4] , [ 78203.72 , 75423.43] , [ 78204.39 , 75422.39] , [ 78204.4 , 75422.39] , [ 78204.39 , 75420.05] , [ 78205.0 , 75417.0] , [ 78211.0 , 75407.0] , [ 78224.89 , 75391.3]]} , "properties" : { "name" : "Ligne autobus: 20"}} , { "type" : "Feature" , "bbox" : [ 78400 , 76638.99 , 78634.63 , 76768.79] , "geometry" : { "type" : "LineString" , "coordinates" : [ [ 78634.63 , 76638.99] , [ 78582.0 , 76722.0] , [ 78565.59 , 76749.01] , [ 78549.0 , 76757.0] , [ 78539.0 , 76764.0] , [ 78527.0 , 76767.0] , [ 78513.0 , 76768.0] , [ 78502.71 , 76768.79] , [ 78501.45 , 76768.63] , [ 78499.7 , 76768.13] , [ 78499.71 , 76768.12] , [ 78400.0 , 76702.02]]} , "properties" : { "name" : "Ligne autobus: 20"}} , { "type" : "Feature" , "bbox" : [ 78674.75 , 76180.25 , 78985.02 , 76554.33] , "geometry" : { "type" : "LineString" , "coordinates" : [ [ 78674.75 , 76554.33] , [ 78687.27 , 76537.53] , [ 78717.19 , 76489.98] , [ 78718.06 , 76488.48] , [ 78752.58 , 76433.78] , [ 78809.24 , 76344.15] , [ 78823.3 , 76321.9] , [ 78898.52 , 76202.86] , [ 78901.06 , 76199.72] , [ 78903.73 , 76194.8] , [ 78906.1 , 76189.59] , [ 78906.39 , 76189.06] , [ 78907.62 , 76186.4] , [ 78909.26 , 76184.96] , [ 78913.97 , 76182.09] , [ 78913.78 , 76182.3] , [ 78918.07 , 76180.45] , [ 78920.33 , 76180.25] , [ 78924.64 , 76181.27] , [ 78985.02 , 76212.4]]} , "properties" : { "name" : "Ligne autobus: 20"}} , { "type" : "Feature" , "bbox" : [ 80047 , 77881.28 , 80352.94 , 78100.06] , "geometry" : { "type" : "LineString" , "coordinates" : [ [ 80352.94 , 78087.44] , [ 80338.99 , 78091.68] , [ 80322.17 , 78097.35] , [ 80309.6 , 78099.81] , [ 80304.05 , 78100.06] , [ 80288.27 , 78099.32] , [ 80273.98 , 78096.23] , [ 80267.33 , 78093.39] , [ 80260.05 , 78089.7] , [ 80252.29 , 78084.77] , [ 80241.81 , 78075.77] , [ 80214.97 , 78049.17] , [ 80191.7 , 78028.27] , [ 80165.25 , 78001.16] , [ 80161.89 , 77997.72] , [ 80136.87 , 77972.32] , [ 80088.33 , 77923.63] , [ 80063.31 , 77896.92] , [ 80047.0 , 77881.28]]} , "properties" : { "name" : "Ligne autobus: 20"}} , { "type" : "Feature" , "bbox" : [ 79671.55 , 75467.81 , 80420.15 , 75629.22] , "geometry" : { "type" : "LineString" , "coordinates" : [ [ 80420.15 , 75585.39] , [ 80392.88 , 75587.65] , [ 80355.7 , 75593.19] , [ 80297.5 , 75605.9] , [ 80266.09 , 75613.98] , [ 80211.36 , 75625.75] , [ 80180.42 , 75629.22] , [ 80149.23 , 75629.22] , [ 80134.92 , 75628.99] , [ 80121.99 , 75627.83] , [ 80113.67 , 75627.14] , [ 80093.12 , 75623.68] , [ 80067.25 , 75617.44] , [ 80053.4 , 75614.67] , [ 80040.93 , 75610.75] , [ 79983.43 , 75591.8] , [ 79929.38 , 75572.64] , [ 79853.64 , 75546.08] , [ 79819.69 , 75532.23] , [ 79812.07 , 75529.45] , [ 79739.84 , 75495.89] , [ 79737.24 , 75494.58] , [ 79703.77 , 75479.23] , [ 79681.52 , 75468.89] , [ 79678.6 , 75467.82] , [ 79677.12 , 75467.81] , [ 79675.04 , 75468.87] , [ 79672.58 , 75470.42] , [ 79671.55 , 75475.07] , [ 79674.67 , 75480.81] , [ 79678.45 , 75484.59] , [ 79683.4 , 75487.89] , [ 79715.05 , 75507.19]]} , "properties" : { "name" : "Ligne autobus: 20"}} , { "type" : "Feature" , "bbox" : [ 80133.26 , 75392.64 , 80468.47 , 75585.39] , "geometry" : { "type" : "LineString" , "coordinates" : [ [ 80133.26 , 75392.64] , [ 80166.53 , 75413.23] , [ 80249.49 , 75463.06] , [ 80287.31 , 75486.81] , [ 80290.23 , 75487.1] , [ 80382.57 , 75468.63] , [ 80385.63 , 75467.69] , [ 80388.61 , 75466.11] , [ 80390.63 , 75463.57] , [ 80391.42 , 75461.39] , [ 80391.98 , 75457.1] , [ 80393.27 , 75452.79] , [ 80397.01 , 75445.89] , [ 80399.64 , 75443.71] , [ 80402.84 , 75441.53] , [ 80405.85 , 75440.44] , [ 80407.79 , 75440.02] , [ 80409.5 , 75440.1] , [ 80411.3 , 75440.5] , [ 80417.45 , 75442.26] , [ 80423.61 , 75445.48] , [ 80428.01 , 75450.17] , [ 80430.94 , 75456.03] , [ 80431.52 , 75462.77] , [ 80428.3 , 75470.68] , [ 80426.9 , 75472.26] , [ 80425.66 , 75478.31] , [ 80425.66 , 75485.64] , [ 80432.11 , 75500.29] , [ 80446.47 , 75527.85] , [ 80452.45 , 75535.11] , [ 80456.21 , 75544.14] , [ 80468.47 , 75562.68] , [ 80466.75 , 75572.09] , [ 80465.33 , 75574.65] , [ 80462.76 , 75577.5] , [ 80459.05 , 75579.21] , [ 80450.79 , 75581.49] , [ 80426.9 , 75585.22] , [ 80423.46 , 75585.19] , [ 80420.15 , 75585.39]]} , "properties" : { "name" : "Ligne autobus: 20"}} , { "type" : "Feature" , "bbox" : [ 78165.56 , 75152.5 , 78545.56 , 75302.27] , "geometry" : { "type" : "LineString" , "coordinates" : [ [ 78165.56 , 75152.5] , [ 78197.79 , 75163.46] , [ 78221.2 , 75173.45] , [ 78261.39 , 75193.81] , [ 78289.24 , 75209.74] , [ 78338.77 , 75240.34] , [ 78395.22 , 75278.18] , [ 78409.08 , 75285.66] , [ 78422.24 , 75289.68] , [ 78453.96 , 75294.39] , [ 78486.39 , 75298.63] , [ 78508.55 , 75301.2] , [ 78520.66 , 75302.27] , [ 78523.65 , 75302.19] , [ 78524.57 , 75302.15] , [ 78528.04 , 75301.54] , [ 78532.37 , 75300.29] , [ 78535.87 , 75298.63] , [ 78538.78 , 75296.65] , [ 78540.88 , 75294.23] , [ 78542.74 , 75291.04] , [ 78544.15 , 75286.44] , [ 78544.9 , 75280.58] , [ 78545.56 , 75270.02]]} , "properties" : { "name" : "Ligne autobus: 20"}} , { "type" : "Feature" , "bbox" : [ 78517.56 , 75187.05 , 78860.49 , 75312.99] , "geometry" : { "type" : "LineString" , "coordinates" : [ [ 78860.49 , 75243.32] , [ 78833.56 , 75233.11] , [ 78796.15 , 75217.76] , [ 78793.28 , 75216.25] , [ 78757.57 , 75201.76] , [ 78746.97 , 75197.99] , [ 78741.77 , 75196.13] , [ 78732.69 , 75193.55] , [ 78718.17 , 75190.4] , [ 78695.87 , 75187.58] , [ 78690.19 , 75187.34] , [ 78679.92 , 75187.05] , [ 78665.3 , 75187.58] , [ 78645.01 , 75190.02] , [ 78633.26 , 75191.73] , [ 78621.7 , 75193.36] , [ 78597.01 , 75198.85] , [ 78575.42 , 75204.48] , [ 78566.11 , 75207.4] , [ 78562.72 , 75208.73] , [ 78560.18 , 75211.22] , [ 78558.18 , 75214.76] , [ 78557.36 , 75218.34] , [ 78556.98 , 75226.03] , [ 78555.46 , 75243.6] , [ 78554.16 , 75260.27] , [ 78551.38 , 75301.92] , [ 78551.29 , 75302.27] , [ 78551.07 , 75303.06] , [ 78550.92 , 75303.53] , [ 78550.32 , 75304.83] , [ 78549.2 , 75306.38] , [ 78548.99 , 75306.62] , [ 78547.27 , 75307.91] , [ 78544.2 , 75309.77] , [ 78541.4 , 75311.27] , [ 78537.97 , 75312.13] , [ 78534.39 , 75312.92] , [ 78531.74 , 75312.99] , [ 78518.92 , 75312.17] , [ 78517.56 , 75312.0]]} , "properties" : { "name" : "Ligne autobus: 20"}} , { "type" : "Feature" , "bbox" : [ 78545.56 , 75180 , 78765.24 , 75270.02] , "geometry" : { "type" : "LineString" , "coordinates" : [ [ 78545.56 , 75270.02] , [ 78550.5 , 75209.76] , [ 78554.5 , 75201.51] , [ 78558.5 , 75199.51] , [ 78565.51 , 75198.51] , [ 78606.03 , 75188.75] , [ 78639.05 , 75183.5] , [ 78664.32 , 75180.75] , [ 78688.84 , 75180.0] , [ 78708.09 , 75181.75] , [ 78720.61 , 75183.75] , [ 78736.36 , 75187.5] , [ 78753.88 , 75193.01] , [ 78765.24 , 75197.51]]} , "properties" : { "name" : "Ligne autobus: 20"}} , { "type" : "Feature" , "bbox" : [ 77851.33 , 75102.44 , 78022.98 , 75133.32] , "geometry" : { "type" : "LineString" , "coordinates" : [ [ 77905.54 , 75133.32] , [ 77899.93 , 75131.26] , [ 77892.27 , 75127.57] , [ 77890.36 , 75126.98] , [ 77886.92 , 75126.49] , [ 77879.44 , 75125.7] , [ 77873.25 , 75124.97] , [ 77865.78 , 75123.53] , [ 77859.39 , 75120.34] , [ 77851.33 , 75115.77] , [ 77851.53 , 75110.67] , [ 77852.65 , 75108.12] , [ 77854.72 , 75106.52] , [ 77858.07 , 75104.77] , [ 77860.62 , 75103.65] , [ 77862.2 , 75103.12] , [ 77863.97 , 75102.69] , [ 77867.14 , 75102.44] , [ 77872.59 , 75103.17] , [ 77894.13 , 75106.52] , [ 77943.28 , 75114.02] , [ 77964.44 , 75117.08] , [ 78022.98 , 75123.98]]} , "properties" : { "name" : "Ligne autobus: 20"}} , { "type" : "Feature" , "bbox" : [ 79786.44 , 77605.41 , 80047 , 77881.28] , "geometry" : { "type" : "LineString" , "coordinates" : [ [ 80047.0 , 77881.28] , [ 80031.13 , 77865.89] , [ 80027.14 , 77862.08] , [ 80012.25 , 77847.7] , [ 80008.32 , 77843.95] , [ 79979.29 , 77816.1] , [ 79968.84 , 77806.03] , [ 79954.18 , 77791.76] , [ 79918.5 , 77756.54] , [ 79897.95 , 77737.35] , [ 79893.45 , 77732.84] , [ 79865.66 , 77702.98] , [ 79824.95 , 77663.12] , [ 79817.47 , 77657.3] , [ 79807.51 , 77654.8] , [ 79804.13 , 77653.53] , [ 79800.46 , 77652.04] , [ 79798.25 , 77650.67] , [ 79792.09 , 77646.48] , [ 79789.88 , 77644.5] , [ 79787.52 , 77639.7] , [ 79786.44 , 77632.32] , [ 79786.54 , 77627.21] , [ 79787.05 , 77623.73] , [ 79788.91 , 77618.51] , [ 79792.97 , 77612.99] , [ 79798.48 , 77608.19] , [ 79803.91 , 77606.45] , [ 79810.42 , 77605.5] , [ 79812.94 , 77605.5] , [ 79812.94 , 77605.41] , [ 79819.04 , 77607.36] , [ 79824.38 , 77609.64] , [ 79826.95 , 77611.21] , [ 79829.14 , 77613.56] , [ 79831.31 , 77616.68] , [ 79834.32 , 77623.68] , [ 79835.7 , 77637.47] , [ 79836.98 , 77643.66] , [ 79851.43 , 77671.11] , [ 79868.0 , 77691.0] , [ 79898.0 , 77721.0] , [ 79906.5 , 77730.2] , [ 79909.51 , 77733.6] , [ 79928.58 , 77750.59] , [ 79930.36 , 77752.51] , [ 79955.77 , 77777.95]]} , "properties" : { "name" : "Ligne autobus: 20"}} , { "type" : "Feature" , "bbox" : [ 80217.23 , 77283.41 , 80536 , 77582.86] , "geometry" : { "type" : "LineString" , "coordinates" : [ [ 80536.0 , 77582.86] , [ 80298.91 , 77360.61] , [ 80279.5 , 77342.2] , [ 80217.23 , 77283.41]]} , "properties" : { "name" : "Ligne autobus: 20"}} , { "type" : "Feature" , "bbox" : [ 80242.86 , 77296.12 , 80541.45 , 77576.65] , "geometry" : { "type" : "LineString" , "coordinates" : [ [ 80242.86 , 77296.12] , [ 80290.56 , 77341.58] , [ 80304.8 , 77355.16] , [ 80420.31 , 77463.76] , [ 80453.72 , 77495.09] , [ 80504.6 , 77541.66] , [ 80541.45 , 77576.65]]} , "properties" : { "name" : "Ligne autobus: 20"}} , { "type" : "Feature" , "bbox" : [ 78385.26 , 76554.33 , 78674.75 , 76755.97] , "geometry" : { "type" : "LineString" , "coordinates" : [ [ 78385.26 , 76682.01] , [ 78479.34 , 76744.6] , [ 78491.49 , 76751.88] , [ 78499.39 , 76754.39] , [ 78509.28 , 76755.97] , [ 78517.69 , 76755.97] , [ 78523.87 , 76754.94] , [ 78531.35 , 76752.59] , [ 78537.91 , 76748.98] , [ 78546.33 , 76742.86] , [ 78551.38 , 76738.37] , [ 78630.76 , 76614.62] , [ 78637.72 , 76606.5] , [ 78641.44 , 76599.81] , [ 78642.66 , 76596.97] , [ 78643.22 , 76594.48] , [ 78643.41 , 76593.04] , [ 78642.7 , 76590.25] , [ 78642.9 , 76581.67] , [ 78642.94 , 76581.56] , [ 78643.35 , 76580.07] , [ 78644.18 , 76578.75] , [ 78646.29 , 76575.77] , [ 78647.26 , 76574.68] , [ 78648.15 , 76573.92] , [ 78650.72 , 76572.41] , [ 78651.99 , 76571.71] , [ 78656.07 , 76569.91] , [ 78656.06 , 76569.91] , [ 78661.47 , 76567.23] , [ 78665.0 , 76564.91] , [ 78666.59 , 76563.43] , [ 78672.91 , 76556.8] , [ 78674.75 , 76554.33]]} , "properties" : { "name" : "Ligne autobus: 20"}} , { "type" : "Feature" , "bbox" : [ 78634.63 , 76189.77 , 78978.8 , 76638.99] , "geometry" : { "type" : "LineString" , "coordinates" : [ [ 78978.8 , 76218.9] , [ 78937.14 , 76197.67] , [ 78924.66 , 76191.28] , [ 78923.95 , 76191.0] , [ 78921.92 , 76190.22] , [ 78919.94 , 76189.77] , [ 78918.35 , 76189.79] , [ 78916.14 , 76190.45] , [ 78914.18 , 76191.35] , [ 78912.31 , 76192.69] , [ 78911.09 , 76194.67] , [ 78909.92 , 76197.8] , [ 78907.58 , 76202.85] , [ 78828.62 , 76324.65] , [ 78814.13 , 76346.64] , [ 78760.0 , 76437.36] , [ 78690.72 , 76553.38] , [ 78682.97 , 76565.31] , [ 78679.89 , 76571.08] , [ 78678.79 , 76574.28] , [ 78677.98 , 76577.91] , [ 78677.49 , 76581.33] , [ 78677.7 , 76585.94] , [ 78677.84 , 76589.26] , [ 78677.77 , 76592.32] , [ 78677.36 , 76594.29] , [ 78675.73 , 76597.61] , [ 78673.76 , 76600.26] , [ 78671.05 , 76602.02] , [ 78668.47 , 76603.17] , [ 78663.99 , 76604.94] , [ 78660.8 , 76606.02] , [ 78659.17 , 76606.57] , [ 78655.1 , 76608.4] , [ 78651.25 , 76612.3] , [ 78634.63 , 76638.99]]} , "properties" : { "name" : "Ligne autobus: 20"}} , { "type" : "Feature" , "bbox" : [ 79971.06 , 77154.76 , 80242.86 , 77296.12] , "geometry" : { "type" : "LineString" , "coordinates" : [ [ 79971.06 , 77154.76] , [ 79974.94 , 77163.45] , [ 79982.01 , 77175.72] , [ 79987.21 , 77184.32] , [ 80002.34 , 77207.93] , [ 80009.81 , 77219.67] , [ 80022.71 , 77238.05] , [ 80035.97 , 77257.17] , [ 80038.99 , 77259.88] , [ 80042.11 , 77261.31] , [ 80044.28 , 77262.02] , [ 80047.18 , 77262.42] , [ 80050.38 , 77261.97] , [ 80054.38 , 77260.02] , [ 80054.41 , 77260.0] , [ 80093.79 , 77233.16] , [ 80104.02 , 77225.73] , [ 80130.2 , 77205.78] , [ 80134.27 , 77204.02] , [ 80137.65 , 77203.66] , [ 80142.99 , 77204.37] , [ 80147.44 , 77207.93] , [ 80161.86 , 77221.91] , [ 80167.7 , 77227.33] , [ 80177.91 , 77234.99] , [ 80204.3 , 77259.68] , [ 80242.86 , 77296.12]]} , "properties" : { "name" : "Ligne autobus: 20"}} , { "type" : "Feature" , "bbox" : [ 77953.5 , 75347.21 , 78222.87 , 75463] , "geometry" : { "type" : "LineString" , "coordinates" : [ [ 78222.87 , 75403.47] , [ 78218.13 , 75409.93] , [ 78214.71 , 75415.9] , [ 78213.81 , 75419.3] , [ 78212.42 , 75422.52] , [ 78211.92 , 75425.14] , [ 78211.72 , 75436.88] , [ 78211.07 , 75438.46] , [ 78210.08 , 75440.03] , [ 78208.19 , 75441.15] , [ 78198.4 , 75444.33] , [ 78188.47 , 75446.84] , [ 78182.0 , 75449.0] , [ 78160.0 , 75455.0] , [ 78149.0 , 75456.0] , [ 78137.0 , 75459.0] , [ 78118.0 , 75461.0] , [ 78102.0 , 75462.0] , [ 78086.0 , 75463.0] , [ 78079.0 , 75463.0] , [ 78072.0 , 75461.0] , [ 78061.0 , 75456.0] , [ 78053.0 , 75452.0] , [ 78045.0 , 75445.0] , [ 78038.0 , 75439.0] , [ 78032.0 , 75431.0] , [ 78019.0 , 75414.0] , [ 78004.0 , 75396.0] , [ 77997.0 , 75387.0] , [ 77974.0 , 75365.0] , [ 77953.5 , 75347.21]]} , "properties" : { "name" : "Ligne autobus: 20"}} , { "type" : "Feature" , "bbox" : [ 80352.94 , 77576.65 , 80707.07 , 78087.44] , "geometry" : { "type" : "LineString" , "coordinates" : [ [ 80541.45 , 77576.65] , [ 80645.77 , 77674.81] , [ 80669.58 , 77697.11] , [ 80675.67 , 77702.95] , [ 80675.7 , 77703.0] , [ 80681.14 , 77705.03] , [ 80691.34 , 77706.78] , [ 80698.33 , 77708.82] , [ 80702.41 , 77712.31] , [ 80704.44 , 77718.43] , [ 80705.9 , 77724.84] , [ 80706.86 , 77732.61] , [ 80707.07 , 77735.32] , [ 80706.77 , 77755.13] , [ 80705.9 , 77767.36] , [ 80702.41 , 77780.46] , [ 80696.58 , 77794.74] , [ 80690.17 , 77806.68] , [ 80670.65 , 77833.18] , [ 80663.08 , 77844.55] , [ 80660.17 , 77852.41] , [ 80660.75 , 77858.52] , [ 80661.16 , 77860.38] , [ 80664.54 , 77871.34] , [ 80665.42 , 77882.12] , [ 80665.2 , 77884.65] , [ 80665.42 , 77890.86] , [ 80655.22 , 77903.38] , [ 80643.57 , 77915.61] , [ 80631.92 , 77917.36] , [ 80621.44 , 77917.65] , [ 80611.53 , 77916.48] , [ 80605.12 , 77918.52] , [ 80597.26 , 77922.61] , [ 80591.26 , 77928.02] , [ 80567.72 , 77955.59] , [ 80547.23 , 77978.9] , [ 80526.65 , 78002.43] , [ 80514.82 , 78014.27] , [ 80502.25 , 78024.62] , [ 80483.14 , 78036.82] , [ 80475.99 , 78040.52] , [ 80462.81 , 78046.19] , [ 80394.03 , 78072.69] , [ 80367.04 , 78082.8] , [ 80352.94 , 78087.44]]} , "properties" : { "name" : "Ligne autobus: 20"}} , { "type" : "Feature" , "bbox" : [ 79966.52 , 77162.37 , 80217.23 , 77283.41] , "geometry" : { "type" : "LineString" , "coordinates" : [ [ 80217.23 , 77283.41] , [ 80161.1 , 77231.01] , [ 80150.86 , 77222.2] , [ 80148.8 , 77220.5] , [ 80145.75 , 77218.07] , [ 80142.46 , 77216.14] , [ 80139.24 , 77214.21] , [ 80137.96 , 77213.89] , [ 80136.19 , 77214.21] , [ 80131.77 , 77216.06] , [ 80126.06 , 77219.28] , [ 80120.47 , 77223.24] , [ 80113.78 , 77227.95] , [ 80088.83 , 77246.96] , [ 80059.86 , 77267.41] , [ 80054.48 , 77269.55] , [ 80050.63 , 77270.19] , [ 80045.17 , 77269.55] , [ 80039.07 , 77267.94] , [ 80032.97 , 77263.6] , [ 80029.91 , 77260.55] , [ 80029.89 , 77260.54] , [ 80025.67 , 77254.72] , [ 79975.0 , 77176.89] , [ 79966.52 , 77162.37]]} , "properties" : { "name" : "Ligne autobus: 20"}} , { "type" : "Feature" , "bbox" : [ 77903.06 , 76225.35 , 78400 , 76702.02] , "geometry" : { "type" : "LineString" , "coordinates" : [ [ 78400.0 , 76702.02] , [ 78380.39 , 76689.01] , [ 78365.41 , 76679.09] , [ 78358.11 , 76674.81] , [ 78354.48 , 76672.78] , [ 78347.0 , 76668.2] , [ 78334.5 , 76660.91] , [ 78294.14 , 76630.82] , [ 78287.55 , 76625.88] , [ 78137.29 , 76519.69] , [ 78112.94 , 76499.72] , [ 78098.76 , 76487.72] , [ 78079.9 , 76471.73] , [ 78062.89 , 76456.36] , [ 78022.91 , 76418.64] , [ 78016.76 , 76411.67] , [ 77994.62 , 76388.3] , [ 77985.4 , 76377.03] , [ 77966.54 , 76353.26] , [ 77954.03 , 76335.21] , [ 77945.31 , 76321.16] , [ 77934.77 , 76303.07] , [ 77932.63 , 76299.22] , [ 77925.89 , 76285.58] , [ 77920.34 , 76272.94] , [ 77912.51 , 76254.16] , [ 77905.2 , 76232.96] , [ 77903.06 , 76225.35]]} , "properties" : { "name" : "Ligne autobus: 20"}} , { "type" : "Feature" , "bbox" : [ 79493.44 , 76581.92 , 79704.59 , 76894.37] , "geometry" : { "type" : "LineString" , "coordinates" : [ [ 79493.44 , 76581.92] , [ 79511.71 , 76599.85] , [ 79530.16 , 76617.89] , [ 79536.72 , 76625.06] , [ 79544.72 , 76635.31] , [ 79552.3 , 76647.4] , [ 79561.31 , 76663.4] , [ 79575.87 , 76691.06] , [ 79591.45 , 76720.58] , [ 79617.68 , 76771.21] , [ 79626.71 , 76787.21] , [ 79633.47 , 76797.04] , [ 79637.57 , 76803.81] , [ 79655.4 , 76827.38] , [ 79704.59 , 76894.37]]} , "properties" : { "name" : "Ligne autobus: 20"}} , { "type" : "Feature" , "bbox" : [ 80076.97 , 77899.05 , 80446.6 , 78090.01] , "geometry" : { "type" : "LineString" , "coordinates" : [ [ 80076.97 , 77899.05] , [ 80197.25 , 78018.36] , [ 80216.29 , 78037.05] , [ 80244.8 , 78064.89] , [ 80250.36 , 78070.92] , [ 80255.41 , 78075.35] , [ 80264.41 , 78081.35] , [ 80269.86 , 78084.01] , [ 80277.5 , 78086.81] , [ 80286.5 , 78088.92] , [ 80292.84 , 78089.68] , [ 80298.5 , 78090.01] , [ 80306.34 , 78089.53] , [ 80315.27 , 78088.24] , [ 80323.25 , 78086.26] , [ 80339.68 , 78080.06] , [ 80377.52 , 78064.38] , [ 80393.68 , 78059.13] , [ 80402.62 , 78054.9] , [ 80423.21 , 78045.01] , [ 80427.09 , 78042.9] , [ 80446.6 , 78035.33] , [ 80446.53 , 78035.4]]} , "properties" : { "name" : "Ligne autobus: 20"}} , { "type" : "Feature" , "bbox" : [ 77957.51 , 75147.91 , 77957.51 , 75147.91] , "geometry" : { "type" : "Point" , "coordinates" : [ 77957.51 , 75147.91]} , "properties" : { "name" : "Ligne autobus: 20 / Rumm<br>Direction(s): Marcel Reuland"}} , { "type" : "Feature" , "bbox" : [ 79704.59 , 76894.37 , 79971.06 , 77154.76] , "geometry" : { "type" : "LineString" , "coordinates" : [ [ 79704.59 , 76894.37] , [ 79785.85 , 77010.52] , [ 79805.46 , 77047.95] , [ 79807.34 , 77050.14] , [ 79820.9 , 77066.36] , [ 79870.8 , 77104.39] , [ 79900.03 , 77125.63] , [ 79903.84 , 77127.69] , [ 79918.93 , 77132.36] , [ 79922.92 , 77133.43] , [ 79924.18 , 77133.7] , [ 79925.9 , 77134.05] , [ 79926.56 , 77134.03] , [ 79927.37 , 77133.88] , [ 79928.2 , 77133.53] , [ 79928.26 , 77133.49] , [ 79928.35 , 77133.51] , [ 79928.63 , 77133.16] , [ 79929.94 , 77131.94] , [ 79931.74 , 77130.67] , [ 79933.53 , 77129.79] , [ 79935.41 , 77129.05] , [ 79936.55 , 77128.83] , [ 79937.74 , 77128.61] , [ 79939.05 , 77128.52] , [ 79940.59 , 77128.57] , [ 79941.9 , 77128.74] , [ 79943.34 , 77129.01] , [ 79945.14 , 77129.62] , [ 79947.54 , 77130.84] , [ 79949.25 , 77132.03] , [ 79950.82 , 77133.56] , [ 79951.88 , 77134.78] , [ 79952.89 , 77136.37] , [ 79953.89 , 77138.64] , [ 79954.37 , 77140.61] , [ 79954.59 , 77143.37] , [ 79955.91 , 77144.64] , [ 79957.1 , 77145.57] , [ 79959.59 , 77146.95] , [ 79962.65 , 77148.15] , [ 79966.52 , 77150.37] , [ 79968.28 , 77151.84] , [ 79971.06 , 77154.76]]} , "properties" : { "name" : "Ligne autobus: 20"}} , { "type" : "Feature" , "bbox" : [ 79670.51 , 76860.78 , 79966.52 , 77162.37] , "geometry" : { "type" : "LineString" , "coordinates" : [ [ 79966.52 , 77162.37] , [ 79963.75 , 77158.12] , [ 79959.32 , 77154.43] , [ 79956.27 , 77152.77] , [ 79954.15 , 77152.21] , [ 79952.76 , 77152.12] , [ 79951.47 , 77152.92] , [ 79950.21 , 77154.36] , [ 79948.9 , 77155.45] , [ 79947.76 , 77156.33] , [ 79946.32 , 77157.11] , [ 79944.88 , 77157.77] , [ 79943.61 , 77158.21] , [ 79942.07 , 77158.6] , [ 79940.32 , 77158.78] , [ 79938.05 , 77158.73] , [ 79936.3 , 77158.43] , [ 79933.93 , 77157.68] , [ 79932.09 , 77156.76] , [ 79930.34 , 77155.54] , [ 79928.29 , 77153.7] , [ 79927.15 , 77152.08] , [ 79926.22 , 77150.51] , [ 79925.48 , 77148.89] , [ 79924.65 , 77146.04] , [ 79924.43 , 77142.45] , [ 79923.82 , 77140.92] , [ 79922.64 , 77139.57] , [ 79920.85 , 77138.45] , [ 79903.51 , 77132.08] , [ 79901.59 , 77131.18] , [ 79900.13 , 77130.45] , [ 79870.08 , 77110.47] , [ 79829.51 , 77082.3] , [ 79817.55 , 77073.12] , [ 79813.23 , 77068.57] , [ 79802.84 , 77056.2] , [ 79794.36 , 77041.21] , [ 79761.17 , 76985.79] , [ 79670.51 , 76860.78]]} , "properties" : { "name" : "Ligne autobus: 20"}} , { "type" : "Feature" , "bbox" : [ 77197.77 , 75226.61 , 77604.8 , 75476.4] , "geometry" : { "type" : "LineString" , "coordinates" : [ [ 77197.77 , 75433.49] , [ 77214.5 , 75438.7] , [ 77225.42 , 75442.91] , [ 77297.28 , 75465.87] , [ 77301.06 , 75467.61] , [ 77308.13 , 75474.29] , [ 77309.3 , 75475.0] , [ 77310.81 , 75476.01] , [ 77321.95 , 75476.4] , [ 77325.07 , 75476.06] , [ 77326.25 , 75476.0] , [ 77329.67 , 75474.03] , [ 77353.17 , 75448.95] , [ 77363.8 , 75438.58] , [ 77379.3 , 75427.01] , [ 77391.9 , 75420.58] , [ 77400.31 , 75414.15] , [ 77408.58 , 75407.32] , [ 77412.78 , 75402.46] , [ 77446.0 , 75348.1] , [ 77452.57 , 75337.59] , [ 77462.16 , 75331.42] , [ 77471.21 , 75331.55] , [ 77481.72 , 75334.31] , [ 77485.92 , 75335.1] , [ 77489.73 , 75334.57] , [ 77493.28 , 75333.26] , [ 77496.69 , 75330.5] , [ 77510.87 , 75307.27] , [ 77519.01 , 75296.36] , [ 77531.88 , 75281.0] , [ 77538.84 , 75274.17] , [ 77566.81 , 75251.19] , [ 77581.91 , 75240.69] , [ 77604.8 , 75226.61]]} , "properties" : { "name" : "Ligne autobus: 20"}} , { "type" : "Feature" , "bbox" : [ 78222.87 , 75403.47 , 78222.87 , 75403.47] , "geometry" : { "type" : "Point" , "coordinates" : [ 78222.87 , 75403.47]} , "properties" : { "name" : "Ligne autobus: 20 / Clausener Bréck Quai 4<br>Direction(s): Marcel Reuland"}} , { "type" : "Feature" , "bbox" : [ 79535.72 , 75479.13 , 79770.68 , 75571.63] , "geometry" : { "type" : "LineString" , "coordinates" : [ [ 79715.05 , 75507.19] , [ 79746.62 , 75526.81] , [ 79757.94 , 75535.3] , [ 79767.15 , 75541.67] , [ 79769.27 , 75544.27] , [ 79769.98 , 75545.92] , [ 79770.68 , 75548.28] , [ 79770.68 , 75552.05] , [ 79766.24 , 75562.66] , [ 79764.75 , 75565.87] , [ 79764.76 , 75565.82] , [ 79762.9 , 75568.57] , [ 79760.07 , 75569.98] , [ 79754.64 , 75571.63] , [ 79750.16 , 75571.4] , [ 79741.43 , 75570.22] , [ 79739.93 , 75569.56] , [ 79665.28 , 75535.28] , [ 79624.36 , 75516.61] , [ 79606.23 , 75508.72] , [ 79605.08 , 75508.41] , [ 79588.78 , 75500.26] , [ 79577.43 , 75495.4] , [ 79551.29 , 75484.75] , [ 79535.72 , 75479.13]]} , "properties" : { "name" : "Ligne autobus: 20"}} , { "type" : "Feature" , "bbox" : [ 77603.18 , 75216.31 , 77953.5 , 75347.21] , "geometry" : { "type" : "LineString" , "coordinates" : [ [ 77953.5 , 75347.21] , [ 77927.5 , 75322.9] , [ 77913.14 , 75314.7] , [ 77891.41 , 75302.41] , [ 77868.87 , 75289.69] , [ 77847.55 , 75276.98] , [ 77828.28 , 75268.79] , [ 77807.37 , 75261.0] , [ 77783.19 , 75254.84] , [ 77762.27 , 75248.28] , [ 77737.27 , 75241.72] , [ 77716.77 , 75235.99] , [ 77694.22 , 75228.61] , [ 77678.23 , 75223.69] , [ 77657.74 , 75217.13] , [ 77648.31 , 75216.31] , [ 77640.51 , 75216.31] , [ 77630.68 , 75218.36] , [ 77619.61 , 75224.51] , [ 77603.18 , 75233.99]]} , "properties" : { "name" : "Ligne autobus: 20"}} , { "type" : "Feature" , "bbox" : [ 77182.41 , 75233.99 , 77603.18 , 75482.28] , "geometry" : { "type" : "LineString" , "coordinates" : [ [ 77603.18 , 75233.99] , [ 77594.29 , 75239.16] , [ 77582.19 , 75246.75] , [ 77560.67 , 75262.74] , [ 77544.68 , 75276.06] , [ 77529.93 , 75290.0] , [ 77519.47 , 75302.71] , [ 77506.76 , 75320.95] , [ 77496.92 , 75335.3] , [ 77494.67 , 75337.14] , [ 77492.21 , 75338.58] , [ 77489.54 , 75339.6] , [ 77486.88 , 75339.4] , [ 77475.4 , 75337.76] , [ 77469.87 , 75336.53] , [ 77467.2 , 75336.53] , [ 77463.51 , 75337.14] , [ 77459.41 , 75339.4] , [ 77455.1 , 75343.3] , [ 77447.52 , 75355.39] , [ 77433.58 , 75378.14] , [ 77416.36 , 75405.41] , [ 77406.93 , 75415.86] , [ 77395.86 , 75424.47] , [ 77383.16 , 75431.24] , [ 77376.19 , 75435.75] , [ 77366.76 , 75442.92] , [ 77355.48 , 75453.99] , [ 77344.62 , 75465.87] , [ 77334.78 , 75476.54] , [ 77331.09 , 75480.02] , [ 77324.74 , 75482.28] , [ 77318.38 , 75481.46] , [ 77315.81 , 75481.21] , [ 77314.49 , 75480.84] , [ 77304.44 , 75477.15] , [ 77293.78 , 75472.29] , [ 77221.66 , 75448.47] , [ 77201.38 , 75442.49] , [ 77187.57 , 75438.58] , [ 77182.41 , 75436.86]]} , "properties" : { "name" : "Ligne autobus: 20"}} , { "type" : "Feature" , "bbox" : [ 80353.72 , 75482.35 , 80353.72 , 75482.35] , "geometry" : { "type" : "Point" , "coordinates" : [ 80353.72 , 75482.35]} , "properties" : { "name" : "Ligne autobus: 20 / Ronndréisch Quai 3<br>Direction(s): Rue de Bitbourg / Fondation Pescatore"}} , { "type" : "Feature" , "bbox" : [ 77182.41 , 75436.86 , 77182.41 , 75436.86] , "geometry" : { "type" : "Point" , "coordinates" : [ 77182.41 , 75436.86]} , "properties" : { "name" : "Ligne autobus: 20 / Badanstalt Quai 2<br>Direction(s): Marcel Reuland"}} , { "type" : "Feature" , "bbox" : [ 80446.53 , 77582.86 , 80699.7 , 78035.4] , "geometry" : { "type" : "LineString" , "coordinates" : [ [ 80446.53 , 78035.4] , [ 80467.19 , 78026.88] , [ 80477.14 , 78021.56] , [ 80485.19 , 78016.99] , [ 80494.59 , 78010.45] , [ 80500.05 , 78006.14] , [ 80508.16 , 77998.85] , [ 80516.14 , 77990.94] , [ 80519.14 , 77987.6] , [ 80536.05 , 77967.29] , [ 80549.07 , 77952.01] , [ 80567.42 , 77930.19] , [ 80573.85 , 77923.25] , [ 80581.35 , 77915.27] , [ 80584.53 , 77911.91] , [ 80587.47 , 77906.8] , [ 80589.37 , 77900.12] , [ 80589.11 , 77898.14] , [ 80584.54 , 77882.47] , [ 80585.1 , 77871.22] , [ 80589.54 , 77858.2] , [ 80590.82 , 77855.21] , [ 80599.53 , 77845.93] , [ 80610.51 , 77839.7] , [ 80617.45 , 77838.26] , [ 80639.9 , 77838.6] , [ 80645.44 , 77837.38] , [ 80653.92 , 77832.68] , [ 80662.23 , 77825.72] , [ 80674.64 , 77813.27] , [ 80682.9 , 77802.99] , [ 80690.97 , 77788.41] , [ 80696.12 , 77774.95] , [ 80698.79 , 77761.89] , [ 80699.7 , 77748.13] , [ 80699.55 , 77743.94] , [ 80698.9 , 77727.08] , [ 80698.82 , 77726.64] , [ 80696.92 , 77722.22] , [ 80694.67 , 77719.96] , [ 80691.59 , 77717.7] , [ 80688.04 , 77716.26] , [ 80683.62 , 77715.4] , [ 80678.0 , 77713.33] , [ 80670.76 , 77708.8] , [ 80665.08 , 77703.82] , [ 80650.52 , 77690.55] , [ 80536.0 , 77582.86]]} , "properties" : { "name" : "Ligne autobus: 20"}} , { "type" : "Feature" , "bbox" : [ 78224.89 , 75391.3 , 78224.89 , 75391.3] , "geometry" : { "type" : "Point" , "coordinates" : [ 78224.89 , 75391.3]} , "properties" : { "name" : "Ligne autobus: 20 / Clausener Bréck Quai 3<br>Direction(s): Rue de Bitbourg / Fondation Pescatore"}} , { "type" : "Feature" , "bbox" : [ 76965.87 , 75724.34 , 77903.06 , 76225.5] , "geometry" : { "type" : "LineString" , "coordinates" : [ [ 77903.06 , 76225.35] , [ 77903.03 , 76225.5] , [ 77902.08 , 76221.87] , [ 77899.41 , 76212.43] , [ 77897.58 , 76206.41] , [ 77887.93 , 76170.09] , [ 77884.34 , 76156.88] , [ 77883.46 , 76154.73] , [ 77878.2 , 76137.82] , [ 77874.31 , 76129.17] , [ 77866.1 , 76109.32] , [ 77862.89 , 76102.68] , [ 77861.14 , 76097.76] , [ 77859.81 , 76092.01] , [ 77857.4 , 76072.85] , [ 77856.6 , 76060.4] , [ 77858.74 , 76044.21] , [ 77858.87 , 76043.51] , [ 77859.78 , 76038.21] , [ 77859.79 , 76038.17] , [ 77858.83 , 76034.9] , [ 77855.94 , 76031.82] , [ 77852.47 , 76029.7] , [ 77846.11 , 76027.95] , [ 77739.98 , 76002.35] , [ 77645.8 , 75980.2] , [ 77619.99 , 75972.31] , [ 77594.55 , 75965.46] , [ 77594.55 , 75965.47] , [ 77542.35 , 75952.67] , [ 77536.69 , 75950.04] , [ 77523.16 , 75945.13] , [ 77510.25 , 75941.64] , [ 77509.22 , 75941.44] , [ 77489.75 , 75935.29] , [ 77482.37 , 75931.4] , [ 77096.02 , 75845.2] , [ 76997.94 , 75823.03] , [ 76995.27 , 75822.48] , [ 76987.48 , 75820.58] , [ 76980.65 , 75817.83] , [ 76976.83 , 75815.84] , [ 76973.01 , 75813.01] , [ 76970.19 , 75808.7] , [ 76967.37 , 75802.39] , [ 76966.71 , 75799.07] , [ 76965.87 , 75795.58] , [ 76966.91 , 75787.58] , [ 76967.04 , 75787.28] , [ 76970.29 , 75779.16] , [ 76989.28 , 75724.34]]} , "properties" : { "name" : "Ligne autobus: 20"}} , { "type" : "Feature" , "bbox" : [ 77197.77 , 75433.49 , 77197.77 , 75433.49] , "geometry" : { "type" : "Point" , "coordinates" : [ 77197.77 , 75433.49]} , "properties" : { "name" : "Ligne autobus: 20 / Badanstalt Quai 1<br>Direction(s): Rue de Bitbourg / Fondation Pescatore"}} , { "type" : "Feature" , "bbox" : [ 80352.94 , 78087.44 , 80352.94 , 78087.44] , "geometry" : { "type" : "Point" , "coordinates" : [ 80352.94 , 78087.44]} , "properties" : { "name" : "Ligne autobus: 20 / Parking Foire<br>Direction(s): Marcel Reuland"}} , { "type" : "Feature" , "bbox" : [ 80446.53 , 78035.4 , 80446.53 , 78035.4] , "geometry" : { "type" : "Point" , "coordinates" : [ 80446.53 , 78035.4]} , "properties" : { "name" : "Ligne autobus: 20 / Parking Foire<br>Direction(s): Rue de Bitbourg / Fondation Pescatore"}} , { "type" : "Feature" , "bbox" : [ 78765.24 , 75197.51 , 78765.24 , 75197.51] , "geometry" : { "type" : "Point" , "coordinates" : [ 78765.24 , 75197.51]} , "properties" : { "name" : "Ligne autobus: 20 / Nic Rollinger<br>Direction(s): Rue de Bitbourg / Fondation Pescatore"}} , { "type" : "Feature" , "bbox" : [ 78860.49 , 75243.32 , 78860.49 , 75243.32] , "geometry" : { "type" : "Point" , "coordinates" : [ 78860.49 , 75243.32]} , "properties" : { "name" : "Ligne autobus: 20 / Nic Rollinger<br>Direction(s): Marcel Reuland"}} , { "type" : "Feature" , "bbox" : [ 79670.51 , 76860.78 , 79670.51 , 76860.78] , "geometry" : { "type" : "Point" , "coordinates" : [ 79670.51 , 76860.78]} , "properties" : { "name" : "Ligne autobus: 20 / Muguets<br>Direction(s): Rue de Bitbourg / Fondation Pescatore"}} , { "type" : "Feature" , "bbox" : [ 78517.56 , 75312 , 78517.56 , 75312] , "geometry" : { "type" : "Point" , "coordinates" : [ 78517.56 , 75312.0]} , "properties" : { "name" : "Ligne autobus: 20 / Fort Dumoulin Quai 2<br>Direction(s): Marcel Reuland"}} , { "type" : "Feature" , "bbox" : [ 77603.18 , 75233.99 , 77603.18 , 75233.99] , "geometry" : { "type" : "Point" , "coordinates" : [ 77603.18 , 75233.99]} , "properties" : { "name" : "Ligne autobus: 20 / Um Bock / Casemates<br>Direction(s): Marcel Reuland"}} , { "type" : "Feature" , "bbox" : [ 77604.8 , 75226.61 , 77604.8 , 75226.61] , "geometry" : { "type" : "Point" , "coordinates" : [ 77604.8 , 75226.61]} , "properties" : { "name" : "Ligne autobus: 20 / Um Bock / Casemates<br>Direction(s): Rue de Bitbourg / Fondation Pescatore"}} , { "type" : "Feature" , "bbox" : [ 78545.56 , 75270.02 , 78545.56 , 75270.02] , "geometry" : { "type" : "Point" , "coordinates" : [ 78545.56 , 75270.02]} , "properties" : { "name" : "Ligne autobus: 20 / Fort Dumoulin Quai 3<br>Direction(s): Rue de Bitbourg / Fondation Pescatore"}} , { "type" : "Feature" , "bbox" : [ 78022.98 , 75123.98 , 78022.98 , 75123.98] , "geometry" : { "type" : "Point" , "coordinates" : [ 78022.98 , 75123.98]} , "properties" : { "name" : "Ligne autobus: 20 / Dinselpuert<br>Direction(s): Rue de Bitbourg / Fondation Pescatore"}} , { "type" : "Feature" , "bbox" : [ 78978.8 , 76218.9 , 78978.8 , 76218.9] , "geometry" : { "type" : "Point" , "coordinates" : [ 78978.8 , 76218.9]} , "properties" : { "name" : "Ligne autobus: 20 / Bleuets<br>Direction(s): Rue de Bitbourg / Fondation Pescatore"}} , { "type" : "Feature" , "bbox" : [ 78126.51 , 75231.22 , 78126.51 , 75231.22] , "geometry" : { "type" : "Point" , "coordinates" : [ 78126.51 , 75231.22]} , "properties" : { "name" : "Ligne autobus: 20 / Tour Jacob<br>Direction(s): Rue de Bitbourg / Fondation Pescatore"}} , { "type" : "Feature" , "bbox" : [ 78190.94 , 75273.73 , 78190.94 , 75273.73] , "geometry" : { "type" : "Point" , "coordinates" : [ 78190.94 , 75273.73]} , "properties" : { "name" : "Ligne autobus: 20 / Tour Jacob<br>Direction(s): Marcel Reuland"}} , { "type" : "Feature" , "bbox" : [ 77028.13 , 75652.49 , 77028.13 , 75652.49] , "geometry" : { "type" : "Point" , "coordinates" : [ 77028.13 , 75652.49]} , "properties" : { "name" : "Ligne autobus: 20 / Fondation Pescatore Quai 1<br>Direction(s): Marcel Reuland"}} , { "type" : "Feature" , "bbox" : [ 76989.28 , 75724.34 , 76989.28 , 75724.34] , "geometry" : { "type" : "Point" , "coordinates" : [ 76989.28 , 75724.34]} , "properties" : { "name" : "Ligne autobus: 20 / Fondation Pescatore Quai 2<br>Direction(s): Rue de Bitbourg / Fondation Pescatore"}} , { "type" : "Feature" , "bbox" : [ 79966.52 , 77162.37 , 79966.52 , 77162.37] , "geometry" : { "type" : "Point" , "coordinates" : [ 79966.52 , 77162.37]} , "properties" : { "name" : "Ligne autobus: 20 / Labours<br>Direction(s): Rue de Bitbourg / Fondation Pescatore"}} , { "type" : "Feature" , "bbox" : [ 79971.06 , 77154.76 , 79971.06 , 77154.76] , "geometry" : { "type" : "Point" , "coordinates" : [ 79971.06 , 77154.76]} , "properties" : { "name" : "Ligne autobus: 20 / Labours<br>Direction(s): Marcel Reuland"}} , { "type" : "Feature" , "bbox" : [ 78385.26 , 76682.01 , 78385.26 , 76682.01] , "geometry" : { "type" : "Point" , "coordinates" : [ 78385.26 , 76682.01]} , "properties" : { "name" : "Ligne autobus: 20 / Jean Monnet<br>Direction(s): Marcel Reuland"}} , { "type" : "Feature" , "bbox" : [ 78400 , 76702.02 , 78400 , 76702.02] , "geometry" : { "type" : "Point" , "coordinates" : [ 78400.0 , 76702.02]} , "properties" : { "name" : "Ligne autobus: 20 / Jean Monnet<br>Direction(s): Rue de Bitbourg / Fondation Pescatore"}} , { "type" : "Feature" , "bbox" : [ 80047 , 77881.28 , 80047 , 77881.28] , "geometry" : { "type" : "Point" , "coordinates" : [ 80047.0 , 77881.28]} , "properties" : { "name" : "Ligne autobus: 20 / Poutty Stein<br>Direction(s): Marcel Reuland"}} , { "type" : "Feature" , "bbox" : [ 80076.97 , 77899.05 , 80076.97 , 77899.05] , "geometry" : { "type" : "Point" , "coordinates" : [ 80076.97 , 77899.05]} , "properties" : { "name" : "Ligne autobus: 20 / Poutty Stein<br>Direction(s): Rue de Bitbourg / Fondation Pescatore"}} , { "type" : "Feature" , "bbox" : [ 78149.38 , 75154.6 , 78149.38 , 75154.6] , "geometry" : { "type" : "Point" , "coordinates" : [ 78149.38 , 75154.6]} , "properties" : { "name" : "Ligne autobus: 20 / Kéibierg-I.N.S.<br>Direction(s): Marcel Reuland"}} , { "type" : "Feature" , "bbox" : [ 78165.56 , 75152.5 , 78165.56 , 75152.5] , "geometry" : { "type" : "Point" , "coordinates" : [ 78165.56 , 75152.5]} , "properties" : { "name" : "Ligne autobus: 20 / Kéibierg-I.N.S.<br>Direction(s): Rue de Bitbourg / Fondation Pescatore"}} , { "type" : "Feature" , "bbox" : [ 79619.42 , 75507.31 , 79619.42 , 75507.31] , "geometry" : { "type" : "Point" , "coordinates" : [ 79619.42 , 75507.31]} , "properties" : { "name" : "Ligne autobus: 20 / Fetschebur<br>Direction(s): Rue de Bitbourg / Fondation Pescatore"}} , { "type" : "Feature" , "bbox" : [ 79535.72 , 75479.13 , 79535.72 , 75479.13] , "geometry" : { "type" : "Point" , "coordinates" : [ 79535.72 , 75479.13]} , "properties" : { "name" : "Ligne autobus: 20 / Fetschebur<br>Direction(s): Marcel Reuland"}} , { "type" : "Feature" , "bbox" : [ 78674.75 , 76554.33 , 78674.75 , 76554.33] , "geometry" : { "type" : "Point" , "coordinates" : [ 78674.75 , 76554.33]} , "properties" : { "name" : "Ligne autobus: 20 / Léon Hengen<br>Direction(s): Marcel Reuland"}} , { "type" : "Feature" , "bbox" : [ 78634.63 , 76638.99 , 78634.63 , 76638.99] , "geometry" : { "type" : "Point" , "coordinates" : [ 78634.63 , 76638.99]} , "properties" : { "name" : "Ligne autobus: 20 / Léon Hengen<br>Direction(s): Rue de Bitbourg / Fondation Pescatore"}} , { "type" : "Feature" , "bbox" : [ 79225.93 , 75347.61 , 79225.93 , 75347.61] , "geometry" : { "type" : "Point" , "coordinates" : [ 79225.93 , 75347.61]} , "properties" : { "name" : "Ligne autobus: 20 / Pommiers<br>Direction(s): Rue de Bitbourg / Fondation Pescatore"}} , { "type" : "Feature" , "bbox" : [ 79218.01 , 75352.72 , 79218.01 , 75352.72] , "geometry" : { "type" : "Point" , "coordinates" : [ 79218.01 , 75352.72]} , "properties" : { "name" : "Ligne autobus: 20 / Pommiers<br>Direction(s): Marcel Reuland"}} , { "type" : "Feature" , "bbox" : [ 80133.26 , 75392.64 , 80133.26 , 75392.64] , "geometry" : { "type" : "Point" , "coordinates" : [ 80133.26 , 75392.64]} , "properties" : { "name" : "Ligne autobus: 20 / Rue de Bitbourg<br>Direction(s): Marcel Reuland / Rue de Bitbourg / Fondation Pescatore"}} , { "type" : "Feature" , "bbox" : [ 77953.5 , 75347.21 , 77953.5 , 75347.21] , "geometry" : { "type" : "Point" , "coordinates" : [ 77953.5 , 75347.21]} , "properties" : { "name" : "Ligne autobus: 20 / Plateau Altmunster<br>Direction(s): Marcel Reuland"}} , { "type" : "Feature" , "bbox" : [ 77971.03 , 75354.33 , 77971.03 , 75354.33] , "geometry" : { "type" : "Point" , "coordinates" : [ 77971.03 , 75354.33]} , "properties" : { "name" : "Ligne autobus: 20 / Plateau Altmunster<br>Direction(s): Rue de Bitbourg / Fondation Pescatore"}} , { "type" : "Feature" , "bbox" : [ 79955.77 , 77777.95 , 79955.77 , 77777.95] , "geometry" : { "type" : "Point" , "coordinates" : [ 79955.77 , 77777.95]} , "properties" : { "name" : "Ligne autobus: 20 / Marcel Reuland<br>Direction(s): Marcel Reuland / Rue de Bitbourg / Fondation Pescatore"}} , { "type" : "Feature" , "bbox" : [ 80536 , 77582.86 , 80536 , 77582.86] , "geometry" : { "type" : "Point" , "coordinates" : [ 80536.0 , 77582.86]} , "properties" : { "name" : "Ligne autobus: 20 / Hôpital Kirchberg<br>Direction(s): Rue de Bitbourg / Fondation Pescatore"}} , { "type" : "Feature" , "bbox" : [ 80541.45 , 77576.65 , 80541.45 , 77576.65] , "geometry" : { "type" : "Point" , "coordinates" : [ 80541.45 , 77576.65]} , "properties" : { "name" : "Ligne autobus: 20 / Hôpital Kirchberg<br>Direction(s): Marcel Reuland"}} , { "type" : "Feature" , "bbox" : [ 79711.59 , 75513.57 , 79711.59 , 75513.57] , "geometry" : { "type" : "Point" , "coordinates" : [ 79711.59 , 75513.57]} , "properties" : { "name" : "Ligne autobus: 20 / Cents-Hamm, Halte CFL<br>Direction(s): Rue de Bitbourg / Fondation Pescatore"}} , { "type" : "Feature" , "bbox" : [ 79715.05 , 75507.19 , 79715.05 , 75507.19] , "geometry" : { "type" : "Point" , "coordinates" : [ 79715.05 , 75507.19]} , "properties" : { "name" : "Ligne autobus: 20 / Cents-Hamm, Halte CFL<br>Direction(s): Marcel Reuland"}} , { "type" : "Feature" , "bbox" : [ 77946.11 , 76308.23 , 77946.11 , 76308.23] , "geometry" : { "type" : "Point" , "coordinates" : [ 77946.11 , 76308.23]} , "properties" : { "name" : "Ligne autobus: 20 / B.E.I.<br>Direction(s): Marcel Reuland"}} , { "type" : "Feature" , "bbox" : [ 77903.06 , 76225.35 , 77903.06 , 76225.35] , "geometry" : { "type" : "Point" , "coordinates" : [ 77903.06 , 76225.35]} , "properties" : { "name" : "Ligne autobus: 20 / B.E.I.<br>Direction(s): Rue de Bitbourg / Fondation Pescatore"}} , { "type" : "Feature" , "bbox" : [ 80217.23 , 77283.41 , 80217.23 , 77283.41] , "geometry" : { "type" : "Point" , "coordinates" : [ 80217.23 , 77283.41]} , "properties" : { "name" : "Ligne autobus: 20 / Joseph Hackin<br>Direction(s): Rue de Bitbourg / Fondation Pescatore"}} , { "type" : "Feature" , "bbox" : [ 80242.86 , 77296.12 , 80242.86 , 77296.12] , "geometry" : { "type" : "Point" , "coordinates" : [ 80242.86 , 77296.12]} , "properties" : { "name" : "Ligne autobus: 20 / Joseph Hackin<br>Direction(s): Marcel Reuland"}} , { "type" : "Feature" , "bbox" : [ 76978.49 , 75652.49 , 77946.11 , 76308.24] , "geometry" : { "type" : "LineString" , "coordinates" : [ [ 77028.13 , 75652.49] , [ 77018.0 , 75681.0] , [ 76984.75 , 75777.97] , [ 76978.49 , 75795.25] , [ 76979.32 , 75798.41] , [ 76979.82 , 75801.56] , [ 76981.65 , 75804.88] , [ 76983.64 , 75807.87] , [ 76986.96 , 75810.69] , [ 76992.94 , 75812.68] , [ 76993.62 , 75812.83] , [ 77050.73 , 75825.93] , [ 77051.39 , 75826.14] , [ 77110.82 , 75839.25] , [ 77142.38 , 75845.89] , [ 77151.45 , 75846.09] , [ 77159.0 , 75848.0] , [ 77306.0 , 75881.0] , [ 77456.0 , 75915.0] , [ 77459.05 , 75915.82] , [ 77550.85 , 75935.56] , [ 77612.51 , 75950.48] , [ 77612.61 , 75950.5] , [ 77683.93 , 75966.68] , [ 77790.21 , 75990.37] , [ 77799.28 , 75992.98] , [ 77802.27 , 75994.25] , [ 77808.46 , 75997.34] , [ 77812.83 , 75999.88] , [ 77815.24 , 76000.68] , [ 77860.82 , 76011.2] , [ 77864.82 , 76012.39] , [ 77866.54 , 76013.42] , [ 77869.99 , 76016.63] , [ 77871.13 , 76019.27] , [ 77871.37 , 76022.71] , [ 77871.02 , 76029.71] , [ 77868.26 , 76042.23] , [ 77864.59 , 76061.05] , [ 77864.71 , 76064.84] , [ 77865.39 , 76072.64] , [ 77868.03 , 76091.36] , [ 77871.25 , 76100.99] , [ 77878.25 , 76117.63] , [ 77890.18 , 76150.92] , [ 77893.4 , 76162.05] , [ 77904.99 , 76205.21] , [ 77915.78 , 76241.37] , [ 77922.67 , 76260.07] , [ 77928.52 , 76273.85] , [ 77935.72 , 76289.01] , [ 77938.76 , 76295.42] , [ 77946.11 , 76308.24] , [ 77946.11 , 76308.23]]} , "properties" : { "name" : "Ligne autobus: 20"}} , { "type" : "Feature" , "bbox" : [ 79659.12 , 75456.34 , 80438.59 , 75618.09] , "geometry" : { "type" : "LineString" , "coordinates" : [ [ 79711.59 , 75513.57] , [ 79686.17 , 75498.74] , [ 79668.49 , 75486.69] , [ 79665.91 , 75484.69] , [ 79660.92 , 75478.18] , [ 79659.12 , 75475.09] , [ 79660.01 , 75468.19] , [ 79662.12 , 75463.81] , [ 79666.68 , 75458.61] , [ 79669.11 , 75456.99] , [ 79672.68 , 75456.34] , [ 79677.72 , 75456.99] , [ 79687.39 , 75460.42] , [ 79710.07 , 75470.68] , [ 79738.51 , 75483.6] , [ 79773.07 , 75499.91] , [ 79785.76 , 75505.98] , [ 79809.55 , 75516.0] , [ 79861.54 , 75537.3] , [ 79973.33 , 75576.76] , [ 80022.5 , 75594.92] , [ 80058.82 , 75605.88] , [ 80092.01 , 75612.77] , [ 80139.61 , 75618.09] , [ 80180.95 , 75617.47] , [ 80191.9 , 75617.15] , [ 80211.63 , 75614.65] , [ 80279.58 , 75599.61] , [ 80368.23 , 75578.36] , [ 80376.34 , 75576.76] , [ 80419.56 , 75566.11] , [ 80430.83 , 75560.15] , [ 80434.45 , 75554.34] , [ 80436.61 , 75551.02] , [ 80438.1 , 75546.22] , [ 80438.59 , 75540.41] , [ 80438.59 , 75533.95] , [ 80437.11 , 75528.48] , [ 80435.48 , 75523.52] , [ 80430.22 , 75511.51] , [ 80422.99 , 75496.58] , [ 80419.27 , 75487.88] , [ 80416.87 , 75484.43] , [ 80414.86 , 75482.35] , [ 80412.15 , 75480.95] , [ 80406.14 , 75479.52] , [ 80402.64 , 75478.22] , [ 80399.19 , 75476.7] , [ 80396.41 , 75475.03] , [ 80394.47 , 75474.76] , [ 80392.84 , 75474.76] , [ 80389.75 , 75475.19] , [ 80385.15 , 75476.04] , [ 80353.72 , 75482.35]]} , "properties" : { "name" : "Ligne autobus: 20"}}]}